feature_mapper-0.1.11.dist-info/METADATA
feature_mapper-0.1.11.dist-info/WHEEL
feature_mapper/.gitignore
feature_mapper/pure.py
feature_mapper/__init__.py
feature_mapper/wrapper.py
feature_mapper/FeatureMapper.py
feature_mapper/feature_mapper/__init__.py
feature_mapper/feature_mapper/ffi.py
feature_mapper/feature_mapper/native.so
feature_mapper-0.1.11.dist-info/RECORD
