Metadata-Version: 2.1
Name: feature-mapper
Version: 0.1.11
Requires-Dist: scipy~=1.3.0
Requires-Dist: cffi~=1.13.0
Requires-Dist: numpy~=1.17.0
Requires-Dist: numpy-indexed~=0.3.5
Summary: Transforms a binary feature matrix by applying a binary mapping matrix.
Home-Page: https://github.com/complexity-science-hub/feature-mapper
Author: Markus Strauss <mstrauss@users.noreply.github.com>
Author-Email: Markus Strauss <mstrauss@users.noreply.github.com>
License: GPL-3.0+
